spib_we/__init__.py
spib_we/spib_binning.py
spib_we/spib_driver.py
spib_we-0.1.0.dist-info/AUTHORS.rst
spib_we-0.1.0.dist-info/LICENSE
spib_we-0.1.0.dist-info/METADATA
spib_we-0.1.0.dist-info/WHEEL
spib_we-0.1.0.dist-info/top_level.txt
spib_we-0.1.0.dist-info/RECORD
