Metadata-Version: 2.1
Name: spib-we
Version: 0.1.0
Summary: This is a WESTPA 2.0 plug-in for SPIB augmented weighted ensemble.
Home-page: https://github.com/wangdedi1997/spib_we
Author: Dedi Wang
Author-email: wangdedi1997@gmail.com
License: MIT license
Keywords: spib_we
Classifier: Development Status :: 2 - Pre-Alpha
Classifier: Intended Audience :: Developers
Classifier: License :: OSI Approved :: MIT License
Classifier: Natural Language :: English
Classifier: Programming Language :: Python :: 3
Classifier: Programming Language :: Python :: 3.6
Classifier: Programming Language :: Python :: 3.7
Classifier: Programming Language :: Python :: 3.8
Requires-Python: >=3.6
License-File: LICENSE
License-File: AUTHORS.rst
